dpyhr/__init__.py
dpyhr/log_dummy.py
dpyhr/normal.py
dpyhr/polling.py
dpyhr/utils.py
dpyhr-0.1.1.dist-info/LICENSE
dpyhr-0.1.1.dist-info/METADATA
dpyhr-0.1.1.dist-info/WHEEL
dpyhr-0.1.1.dist-info/RECORD
