Metadata-Version: 2.1
Name: dpyhr
Version: 0.1.1
Summary: dpyhr. A discord.py module reloader written in pure python!
Home-page: https://github.com/timelessnesses/dpyhr
License: MIT
Author: timelessnesses
Author-email: mooping3roblox@gmail.com
Requires-Python: >=3.8,<4.0
Classifier: License :: OSI Approved :: MIT License
Classifier: Programming Language :: Python :: 3
Classifier: Programming Language :: Python :: 3.8
Classifier: Programming Language :: Python :: 3.9
Classifier: Programming Language :: Python :: 3.10
Classifier: Programming Language :: Python :: 3.11
Requires-Dist: decohints (>=1.0.7,<2.0.0)
Requires-Dist: watchdog (>=2.2.1,<3.0.0)
Project-URL: Repository, https://github.com/timelessnesses/dpyhr
